{
  "id": "MAP_ROUTE101",
  "name": "Route101",
  "layout": "LAYOUT_ROUTE101",
  "music": "MUS_ROUTE101",
  "region_map_section": "MAPSEC_ROUTE_101",
  "requires_flash": false,
  "weather": "WEATHER_SUNNY",
  "map_type": "MAP_TYPE_ROUTE",
  "allow_cycling": true,
  "allow_escaping": false,
  "allow_running": true,
  "show_map_name": true,
  "battle_scene": "MAP_BATTLE_SCENE_NORMAL",
  "connections": [
    {
      "map": "MAP_OLDALE_TOWN",
      "offset": 0,
      "direction": "up"
    },
    {
      "map": "MAP_NULLTOWN",
      "offset": 0,
      "direction": "down"
    }
  ],
  "object_events": [
    {
      "graphics_id": "OBJ_EVENT_GFX_YOUNGSTER",
      "x": 5,
      "y": 14,
      "elevation": 3,
      "movement_type": "MOVEMENT_TYPE_FACE_UP",
      "movement_range_x": 0,
      "movement_range_y": 0,
      "trainer_type": "TRAINER_TYPE_NONE",
      "trainer_sight_or_berry_tree_id": "0",
      "script": "Route101_EventScript_TutorialNPC1",
      "flag": "0"
    },
    {
      "graphics_id": "OBJ_EVENT_GFX_HIKER",
      "x": 10,
      "y": 13,
      "elevation": 3,
      "movement_type": "MOVEMENT_TYPE_LOOK_AROUND",
      "movement_range_x": 0,
      "movement_range_y": 0,
      "trainer_type": "TRAINER_TYPE_NONE",
      "trainer_sight_or_berry_tree_id": "0",
      "script": "Route101_EventScript_TutorialNPC2",
      "flag": "0"
    },
    {
      "graphics_id": "OBJ_EVENT_GFX_WOMAN_2",
      "x": 7,
      "y": 9,
      "elevation": 3,
      "movement_type": "MOVEMENT_TYPE_FACE_RIGHT",
      "movement_range_x": 0,
      "movement_range_y": 0,
      "trainer_type": "TRAINER_TYPE_NONE",
      "trainer_sight_or_berry_tree_id": "0",
      "script": "Route101_EventScript_TutorialNPC3",
      "flag": "0"
    },
    {
      "graphics_id": "OBJ_EVENT_GFX_BOY_1",
      "x": 4,
      "y": 8,
      "elevation": 3,
      "movement_type": "MOVEMENT_TYPE_FACE_DOWN",
      "movement_range_x": 0,
      "movement_range_y": 0,
      "trainer_type": "TRAINER_TYPE_NONE",
      "trainer_sight_or_berry_tree_id": "0",
      "script": "Route101_EventScript_TutorialNPC4",
      "flag": "0"
    },
    {
      "graphics_id": "OBJ_EVENT_GFX_MAN_1",
      "x": 4,
      "y": 4,
      "elevation": 3,
      "movement_type": "MOVEMENT_TYPE_FACE_LEFT",
      "movement_range_x": 0,
      "movement_range_y": 0,
      "trainer_type": "TRAINER_TYPE_NONE",
      "trainer_sight_or_berry_tree_id": "0",
      "script": "Route101_EventScript_TutorialNPC5",
      "flag": "0"
    },
    {
      "graphics_id": "OBJ_EVENT_GFX_SCIENTIST_1",
      "x": 8,
      "y": 8,
      "elevation": 3,
      "movement_type": "MOVEMENT_TYPE_FACE_RIGHT",
      "movement_range_x": 0,
      "movement_range_y": 0,
      "trainer_type": "TRAINER_TYPE_NONE",
      "trainer_sight_or_berry_tree_id": "0",
      "script": "Route101_EventScript_BureauEmployee1",
      "flag": "0"
    },
    {
      "graphics_id": "OBJ_EVENT_GFX_SCIENTIST_2",
      "x": 2,
      "y": 14,
      "elevation": 3,
      "movement_type": "MOVEMENT_TYPE_FACE_DOWN",
      "movement_range_x": 0,
      "movement_range_y": 0,
      "trainer_type": "TRAINER_TYPE_NONE",
      "trainer_sight_or_berry_tree_id": "0",
      "script": "Route101_EventScript_BureauEmployee2",
      "flag": "0"
    },
    {
      "graphics_id": "OBJ_EVENT_GFX_SCIENTIST_1",
      "x": 6,
      "y": 6,
      "elevation": 3,
      "movement_type": "MOVEMENT_TYPE_WANDER_LEFT_AND_RIGHT",
      "movement_range_x": 1,
      "movement_range_y": 0,
      "trainer_type": "TRAINER_TYPE_NONE",
      "trainer_sight_or_berry_tree_id": "0",
      "script": "Route101_EventScript_BureauEmployee3",
      "flag": "0"
    },
    {
      "graphics_id": "OBJ_EVENT_GFX_BUG_CATCHER",
      "x": 0,
      "y": 6,
      "elevation": 3,
      "movement_type": "MOVEMENT_TYPE_FACE_RIGHT",
      "movement_range_x": 0,
      "movement_range_y": 0,
      "trainer_type": "TRAINER_TYPE_NORMAL",
      "trainer_sight_or_berry_tree_id": "3",
      "script": "Route101_EventScript_Kyle",
      "flag": "0"
    },
    {
      "graphics_id": "OBJ_EVENT_GFX_LASS",
      "x": 7,
      "y": 11,
      "elevation": 3,
      "movement_type": "MOVEMENT_TYPE_FACE_LEFT",
      "movement_range_x": 0,
      "movement_range_y": 0,
      "trainer_type": "TRAINER_TYPE_NORMAL",
      "trainer_sight_or_berry_tree_id": "2",
      "script": "Route101_EventScript_Penny",
      "flag": "0"
    },
    {
      "graphics_id": "OBJ_EVENT_GFX_ITEM_BALL",
      "x": 0,
      "y": 13,
      "elevation": 3,
      "movement_type": "MOVEMENT_TYPE_FACE_DOWN",
      "movement_range_x": 0,
      "movement_range_y": 0,
      "trainer_type": "TRAINER_TYPE_NONE",
      "trainer_sight_or_berry_tree_id": "0",
      "script": "Route101_EventScript_ItemPotion",
      "flag": "FLAG_ITEM_ROUTE_N1_POTION"
    },
    {
      "graphics_id": "OBJ_EVENT_GFX_YOUNGSTER",
      "x": 8,
      "y": 1,
      "elevation": 3,
      "movement_type": "MOVEMENT_TYPE_FACE_DOWN",
      "movement_range_x": 0,
      "movement_range_y": 0,
      "trainer_type": "TRAINER_TYPE_NORMAL",
      "trainer_sight_or_berry_tree_id": "2",
      "script": "Route101_EventScript_Brad",
      "flag": "0"
    },
    {
      "graphics_id": "OBJ_EVENT_GFX_BEAUTY",
      "x": 7,
      "y": 5,
      "elevation": 3,
      "movement_type": "MOVEMENT_TYPE_FACE_LEFT",
      "movement_range_x": 0,
      "movement_range_y": 0,
      "trainer_type": "TRAINER_TYPE_NORMAL",
      "trainer_sight_or_berry_tree_id": "3",
      "script": "Route101_EventScript_Trixie",
      "flag": "0"
    },
    {
      "graphics_id": "OBJ_EVENT_GFX_CAMPER",
      "x": 6,
      "y": 15,
      "elevation": 3,
      "movement_type": "MOVEMENT_TYPE_FACE_UP",
      "movement_range_x": 0,
      "movement_range_y": 0,
      "trainer_type": "TRAINER_TYPE_NORMAL",
      "trainer_sight_or_berry_tree_id": "2",
      "script": "Route101_EventScript_Dave",
      "flag": "0"
    },
    {
      "graphics_id": "OBJ_EVENT_GFX_RICH_BOY",
      "x": 13,
      "y": 15,
      "elevation": 3,
      "movement_type": "MOVEMENT_TYPE_FACE_LEFT",
      "movement_range_x": 0,
      "movement_range_y": 0,
      "trainer_type": "TRAINER_TYPE_NORMAL",
      "trainer_sight_or_berry_tree_id": "2",
      "script": "Route101_EventScript_Sterling",
      "flag": "0"
    },
    {
      "graphics_id": "OBJ_EVENT_GFX_PICNICKER",
      "x": 3,
      "y": 10,
      "elevation": 3,
      "movement_type": "MOVEMENT_TYPE_FACE_RIGHT",
      "movement_range_x": 0,
      "movement_range_y": 0,
      "trainer_type": "TRAINER_TYPE_NORMAL",
      "trainer_sight_or_berry_tree_id": "2",
      "script": "Route101_EventScript_Marge",
      "flag": "0"
    },
    {
      "graphics_id": "OBJ_EVENT_GFX_OLD_WOMAN",
      "x": 6,
      "y": 2,
      "elevation": 3,
      "movement_type": "MOVEMENT_TYPE_FACE_DOWN",
      "movement_range_x": 0,
      "movement_range_y": 0,
      "trainer_type": "TRAINER_TYPE_NONE",
      "trainer_sight_or_berry_tree_id": "0",
      "script": "Route101_EventScript_GivePotion",
      "flag": "0"
    },
    {
      "graphics_id": "OBJ_EVENT_GFX_FAT_MAN",
      "x": 3,
      "y": 7,
      "elevation": 3,
      "movement_type": "MOVEMENT_TYPE_FACE_LEFT",
      "movement_range_x": 0,
      "movement_range_y": 0,
      "trainer_type": "TRAINER_TYPE_NONE",
      "trainer_sight_or_berry_tree_id": "0",
      "script": "Route101_EventScript_GiveOranBerry",
      "flag": "0"
    },
    {
      "graphics_id": "OBJ_EVENT_GFX_SAILOR",
      "x": 16,
      "y": 15,
      "elevation": 3,
      "movement_type": "MOVEMENT_TYPE_LOOK_AROUND",
      "movement_range_x": 0,
      "movement_range_y": 0,
      "trainer_type": "TRAINER_TYPE_NONE",
      "trainer_sight_or_berry_tree_id": "0",
      "script": "Route101_EventScript_GiveRepel",
      "flag": "0"
    },
    {
      "graphics_id": "OBJ_EVENT_GFX_GIRL_1",
      "x": 11,
      "y": 5,
      "elevation": 3,
      "movement_type": "MOVEMENT_TYPE_FACE_RIGHT",
      "movement_range_x": 0,
      "movement_range_y": 0,
      "trainer_type": "TRAINER_TYPE_NONE",
      "trainer_sight_or_berry_tree_id": "0",
      "script": "Route101_EventScript_GiveAntidote",
      "flag": "0"
    },
    {
      "graphics_id": "OBJ_EVENT_GFX_POKEFAN_F",
      "x": 2,
      "y": 10,
      "elevation": 3,
      "movement_type": "MOVEMENT_TYPE_FACE_UP",
      "movement_range_x": 0,
      "movement_range_y": 0,
      "trainer_type": "TRAINER_TYPE_NONE",
      "trainer_sight_or_berry_tree_id": "0",
      "script": "Route101_EventScript_GiveGreatBall",
      "flag": "0"
    },
    {
      "graphics_id": "OBJ_EVENT_GFX_EXPERT_M",
      "x": 9,
      "y": 1,
      "elevation": 3,
      "movement_type": "MOVEMENT_TYPE_FACE_DOWN",
      "movement_range_x": 0,
      "movement_range_y": 0,
      "trainer_type": "TRAINER_TYPE_NONE",
      "trainer_sight_or_berry_tree_id": "0",
      "script": "Route101_EventScript_AdviceCompat",
      "flag": "0"
    },
    {
      "graphics_id": "OBJ_EVENT_GFX_NINJA_BOY",
      "x": 5,
      "y": 9,
      "elevation": 3,
      "movement_type": "MOVEMENT_TYPE_FACE_LEFT",
      "movement_range_x": 0,
      "movement_range_y": 0,
      "trainer_type": "TRAINER_TYPE_NONE",
      "trainer_sight_or_berry_tree_id": "0",
      "script": "Route101_EventScript_AdviceMoves",
      "flag": "0"
    },
    {
      "graphics_id": "OBJ_EVENT_GFX_OLD_MAN",
      "x": 9,
      "y": 11,
      "elevation": 3,
      "movement_type": "MOVEMENT_TYPE_FACE_RIGHT",
      "movement_range_x": 0,
      "movement_range_y": 0,
      "trainer_type": "TRAINER_TYPE_NONE",
      "trainer_sight_or_berry_tree_id": "0",
      "script": "Route101_EventScript_AdviceBreeding",
      "flag": "0"
    },
    {
      "graphics_id": "OBJ_EVENT_GFX_WOMAN_4",
      "x": 11,
      "y": 7,
      "elevation": 3,
      "movement_type": "MOVEMENT_TYPE_FACE_LEFT",
      "movement_range_x": 0,
      "movement_range_y": 0,
      "trainer_type": "TRAINER_TYPE_NONE",
      "trainer_sight_or_berry_tree_id": "0",
      "script": "Route101_EventScript_AdviceItems",
      "flag": "0"
    },
    {
      "graphics_id": "OBJ_EVENT_GFX_COOK",
      "x": 9,
      "y": 15,
      "elevation": 3,
      "movement_type": "MOVEMENT_TYPE_FACE_UP",
      "movement_range_x": 0,
      "movement_range_y": 0,
      "trainer_type": "TRAINER_TYPE_NONE",
      "trainer_sight_or_berry_tree_id": "0",
      "script": "Route101_EventScript_AdvicePP",
      "flag": "0"
    },
    {
      "graphics_id": "OBJ_EVENT_GFX_ITEM_BALL",
      "x": 11,
      "y": 14,
      "elevation": 3,
      "movement_type": "MOVEMENT_TYPE_NONE",
      "movement_range_x": 0,
      "movement_range_y": 0,
      "trainer_type": "TRAINER_TYPE_NONE",
      "trainer_sight_or_berry_tree_id": "0",
      "script": "Route101_EventScript_Item1",
      "flag": "0"
    }
  ],
  "warp_events": [],
  "coord_events": [
    {
      "type": "trigger",
      "x": 8,
      "y": 0,
      "elevation": 3,
      "var": "VAR_ROUTE_N1_EXIT_TRIGGER",
      "var_value": "0",
      "script": "Route101_EventScript_ExitFakeout"
    },
    {
      "type": "trigger",
      "x": 9,
      "y": 0,
      "elevation": 3,
      "var": "VAR_ROUTE_N1_EXIT_TRIGGER",
      "var_value": "0",
      "script": "Route101_EventScript_ExitFakeout"
    },
    {
      "type": "trigger",
      "x": 10,
      "y": 0,
      "elevation": 3,
      "var": "VAR_ROUTE_N1_EXIT_TRIGGER",
      "var_value": "0",
      "script": "Route101_EventScript_ExitFakeout"
    },
    {
      "type": "trigger",
      "x": 11,
      "y": 0,
      "elevation": 3,
      "var": "VAR_ROUTE_N1_EXIT_TRIGGER",
      "var_value": "0",
      "script": "Route101_EventScript_ExitFakeout"
    }
  ],
  "bg_events": [
    {
      "type": "sign",
      "x": 10,
      "y": 16,
      "elevation": 0,
      "player_facing_dir": "BG_EVENT_PLAYER_FACING_ANY",
      "script": "Route101_EventScript_Sign1"
    },
    {
      "type": "hidden_item",
      "x": 6,
      "y": 12,
      "elevation": 0,
      "item": "ITEM_ANTIDOTE",
      "flag": "FLAG_HIDDEN_ITEM_ROUTE_N1_ANTIDOTE"
    }
  ]
}
