[{"method": "stamp_trees", "sources": [], "detail": "crown"}, {"method": "stamp_trees", "sources": [], "detail": "crown"}, {"method": "stamp_trees", "sources": [], "detail": "crown"}, {"method": "stamp_trees", "sources": [], "detail": "crown"}, {"method": "stamp_trees", "sources": [], "detail": "crown"}, {"method": "stamp_trees", "sources": [], "detail": "crown"}, {"method": "stamp_trees", "sources": [], "detail": "crown"}, {"method": "stamp_trees", "sources": [], "detail": "crown"}, {"method": "stamp_trees", "sources": [], "detail": "crown"}, {"method": "stamp_trees", "sources": [], "detail": "crown"}, {"method": "stamp_trees", "sources": [], "detail": "crown"}, {"method": "stamp_trees", "sources": [], "detail": "crown"}, {"method": "connection_seed", "sources": [], "detail": "from=OldaleTown dir=up tree=False"}, {"method": "connection_seed", "sources": [], "detail": "from=OldaleTown dir=up tree=False"}, {"method": "connection_seed", "sources": [], "detail": "from=OldaleTown dir=up tree=False"}, {"method": "connection_seed", "sources": [], "detail": "from=OldaleTown dir=up tree=False"}, {"method": "stamp_trees", "sources": [], "detail": "crown"}, {"method": "stamp_trees", "sources": [], "detail": "crown"}, {"method": "stamp_trees", "sources": [], "detail": "crown"}, {"method": "stamp_trees", "sources": [], "detail": "crown"}, {"method": "stamp_trees", "sources": [], "detail": "crown"}, {"method": "stamp_trees", "sources": [], "detail": "crown"}, {"method": "stamp_trees", "sources": [], "detail": "crown"}, {"method": "stamp_trees", "sources": [], "detail": "crown"}, {"method": "stamp_trees", "sources": [], "detail": "crown"}, {"method": "stamp_trees", "sources": [], "detail": "crown"}, {"method": "stamp_trees", "sources": [], "detail": "trunk"}, {"method": "stamp_trees", "sources": [], "detail": "trunk"}, {"method": "stamp_trees", "sources": [], "detail": "trunk"}, {"method": "stamp_trees", "sources": [], "detail": "trunk"}, {"method": "stamp_trees", "sources": [], "detail": "trunk"}, {"method": "stamp_trees", "sources": [], "detail": "trunk"}, {"method": "stamp_trees", "sources": [], "detail": "bottom_trunk"}, {"method": "stamp_trees", "sources": [], "detail": "bottom_trunk"}, {"method": "stamp_trees", "sources": [], "detail": "bottom_trunk"}, {"method": "stamp_trees", "sources": [], "detail": "bottom_trunk"}, {"method": "stamp_trees", "sources": [], "detail": "bottom_trunk"}, {"method": "stamp_trees", "sources": [], "detail": "bottom_trunk"}, {"method": "seed_zone", "sources": [], "detail": "zone=path"}, {"method": "seed_zone", "sources": [], "detail": "zone=path"}, {"method": "stamp_trees", "sources": [], "detail": "unpaired_fallback_grass"}, {"method": "stamp_trees", "sources": [], "detail": "unpaired_fallback_grass"}, {"method": "stamp_trees", "sources": [], "detail": "bottom_trunk"}, {"method": "stamp_trees", "sources": [], "detail": "bottom_trunk"}, {"method": "stamp_trees", "sources": [], "detail": "trunk"}, {"method": "stamp_trees", "sources": [], "detail": "trunk"}, {"method": "stamp_trees", "sources": [], "detail": "trunk"}, {"method": "stamp_trees", "sources": [], "detail": "trunk"}, {"method": "stamp_trees", "sources": [], "detail": "trunk"}, {"method": "stamp_trees", "sources": [], "detail": "trunk"}, {"method": "stamp_trees", "sources": [], "detail": "trunk"}, {"method": "stamp_trees", "sources": [], "detail": "trunk"}, {"method": "stamp_trees", "sources": [], "detail": "crown"}, {"method": "stamp_trees", "sources": [], "detail": "crown"}, {"method": "stamp_trees", "sources": [], "detail": "crown"}, {"method": "stamp_trees", "sources": [], "detail": "crown"}, {"method": "stamp_trees", "sources": [], "detail": "crown"}, {"method": "stamp_trees", "sources": [], "detail": "crown"}, {"method": "stamp_trees", "sources": [], "detail": "unpaired_fallback_grass"}, {"method": "stamp_trees", "sources": [], "detail": "unpaired_fallback_grass"}, {"method": "stamp_trees", "sources": [], "detail": "unpaired_fallback_grass"}, {"method": "stamp_trees", "sources": [], "detail": "unpaired_fallback_grass"}, {"method": "stamp_trees", "sources": [], "detail": "unpaired_fallback_grass"}, {"method": "stamp_trees", "sources": [], "detail": "unpaired_fallback_grass"}, {"method": "seed_zone", "sources": [], "detail": "zone=path"}, {"method": "seed_zone", "sources": [], "detail": "zone=path"}, {"method": "seed_zone", "sources": [], "detail": "zone=grass"}, {"method": "seed_zone", "sources": [], "detail": "zone=grass"}, {"method": "stamp_trees", "sources": [], "detail": "unpaired_fallback_grass"}, {"method": "stamp_trees", "sources": [], "detail": "unpaired_fallback_grass"}, {"method": "stamp_trees", "sources": [], "detail": "crown"}, {"method": "stamp_trees", "sources": [], "detail": "crown"}, {"method": "stamp_trees", "sources": [], "detail": "crown"}, {"method": "stamp_trees", "sources": [], "detail": "crown"}, {"method": "stamp_trees", "sources": [], "detail": "crown"}, {"method": "stamp_trees", "sources": [], "detail": "crown"}, {"method": "stamp_trees", "sources": [], "detail": "crown"}, {"method": "stamp_trees", "sources": [], "detail": "crown"}, {"method": "stamp_trees", "sources": [], "detail": "trunk"}, {"method": "stamp_trees", "sources": [], "detail": "trunk"}, {"method": "stamp_trees", "sources": [], "detail": "trunk"}, {"method": "stamp_trees", "sources": [], "detail": "trunk"}, {"method": "stamp_trees", "sources": [], "detail": "bottom_trunk"}, {"method": "stamp_trees", "sources": [], "detail": "bottom_trunk"}, {"method": "seed_zone", "sources": [], "detail": "zone=grass"}, {"method": "seed_zone", "sources": [], "detail": "zone=grass"}, {"method": "seed_zone", "sources": [], "detail": "zone=grass"}, {"method": "seed_zone", "sources": [], "detail": "zone=path"}, {"method": "seed_zone", "sources": [], "detail": "zone=path"}, {"method": "seed_zone", "sources": [], "detail": "zone=path"}, {"method": "seed_zone", "sources": [], "detail": "zone=path"}, {"method": "seed_zone", "sources": [], "detail": "zone=grass"}, {"method": "seed_zone", "sources": [], "detail": "zone=grass"}, {"method": "seed_zone", "sources": [], "detail": "zone=grass"}, {"method": "stamp_trees", "sources": [], "detail": "crown_tip_grass"}, {"method": "stamp_trees", "sources": [], "detail": "crown_tip"}, {"method": "stamp_trees", "sources": [], "detail": "trunk"}, {"method": "stamp_trees", "sources": [], "detail": "trunk"}, {"method": "stamp_trees", "sources": [], "detail": "trunk"}, {"method": "stamp_trees", "sources": [], "detail": "trunk"}, {"method": "stamp_trees", "sources": [], "detail": "trunk"}, {"method": "stamp_trees", "sources": [], "detail": "trunk"}, {"method": "stamp_trees", "sources": [], "detail": "trunk"}, {"method": "stamp_trees", "sources": [], "detail": "trunk"}, {"method": "stamp_trees", "sources": [], "detail": "crown"}, {"method": "stamp_trees", "sources": [], "detail": "crown"}, {"method": "stamp_trees", "sources": [], "detail": "crown"}, {"method": "stamp_trees", "sources": [], "detail": "crown"}, {"method": "stamp_trees", "sources": [], "detail": "unpaired_fallback_grass"}, {"method": "seed_zone", "sources": [], "detail": "zone=grass"}, {"method": "seed_zone", "sources": [], "detail": "zone=grass"}, {"method": "seed_zone", "sources": [], "detail": "zone=grass"}, {"method": "seed_zone", "sources": [], "detail": "zone=grass"}, {"method": "seed_zone", "sources": [], "detail": "zone=path"}, {"method": "seed_zone", "sources": [], "detail": "zone=path"}, {"method": "seed_zone", "sources": [], "detail": "zone=path"}, {"method": "seed_zone", "sources": [], "detail": "zone=grass"}, {"method": "seed_zone", "sources": [], "detail": "zone=grass"}, {"method": "seed_zone", "sources": [], "detail": "zone=grass"}, {"method": "seed_zone", "sources": [], "detail": "zone=grass"}, {"method": "stamp_trees", "sources": [], "detail": "crown"}, {"method": "stamp_trees", "sources": [], "detail": "crown"}, {"method": "stamp_trees", "sources": [], "detail": "crown"}, {"method": "stamp_trees", "sources": [], "detail": "crown"}, {"method": "stamp_trees", "sources": [], "detail": "crown"}, {"method": "stamp_trees", "sources": [], "detail": "crown"}, {"method": "stamp_trees", "sources": [], "detail": "crown"}, {"method": "stamp_trees", "sources": [], "detail": "crown"}, {"method": "stamp_trees", "sources": [], "detail": "crown"}, {"method": "stamp_trees", "sources": [], "detail": "crown"}, {"method": "stamp_trees", "sources": [], "detail": "trunk"}, {"method": "stamp_trees", "sources": [], "detail": "trunk"}, {"method": "stamp_trees", "sources": [], "detail": "trunk"}, {"method": "stamp_trees", "sources": [], "detail": "trunk"}, {"method": "seed_zone", "sources": [], "detail": "zone=grass"}, {"method": "seed_zone", "sources": [], "detail": "zone=grass"}, {"method": "seed_zone", "sources": [], "detail": "zone=grass"}, {"method": "seed_zone", "sources": [], "detail": "zone=grass"}, {"method": "seed_zone", "sources": [], "detail": "zone=path"}, {"method": "seed_zone", "sources": [], "detail": "zone=path"}, {"method": "seed_zone", "sources": [], "detail": "zone=path"}, {"method": "seed_zone", "sources": [], "detail": "zone=path"}, {"method": "seed_zone", "sources": [], "detail": "zone=grass"}, {"method": "seed_zone", "sources": [], "detail": "zone=grass"}, {"method": "seed_zone", "sources": [], "detail": "zone=grass"}, {"method": "stamp_trees", "sources": [], "detail": "unpaired_fallback_grass"}, {"method": "stamp_trees", "sources": [], "detail": "trunk"}, {"method": "stamp_trees", "sources": [], "detail": "trunk"}, {"method": "stamp_trees", "sources": [], "detail": "trunk"}, {"method": "stamp_trees", "sources": [], "detail": "trunk"}, {"method": "stamp_trees", "sources": [], "detail": "trunk"}, {"method": "stamp_trees", "sources": [], "detail": "trunk"}, {"method": "stamp_trees", "sources": [], "detail": "trunk"}, {"method": "stamp_trees", "sources": [], "detail": "trunk"}, {"method": "stamp_trees", "sources": [], "detail": "trunk"}, {"method": "stamp_trees", "sources": [], "detail": "trunk"}, {"method": "stamp_trees", "sources": [], "detail": "crown"}, {"method": "stamp_trees", "sources": [], "detail": "crown"}, {"method": "stamp_trees", "sources": [], "detail": "crown"}, {"method": "stamp_trees", "sources": [], "detail": "crown"}, {"method": "seed_zone", "sources": [], "detail": "zone=grass"}, {"method": "seed_zone", "sources": [], "detail": "zone=grass"}, {"method": "seed_zone", "sources": [], "detail": "zone=grass"}, {"method": "seed_zone", "sources": [], "detail": "zone=path"}, {"method": "seed_zone", "sources": [], "detail": "zone=path"}, {"method": "seed_zone", "sources": [], "detail": "zone=path"}, {"method": "seed_zone", "sources": [], "detail": "zone=path"}, {"method": "seed_zone", "sources": [], "detail": "zone=path"}, {"method": "seed_zone", "sources": [], "detail": "zone=grass"}, {"method": "seed_zone", "sources": [], "detail": "zone=grass"}, {"method": "seed_zone", "sources": [], "detail": "zone=grass"}, {"method": "stamp_trees", "sources": [], "detail": "unpaired_fallback_grass"}, {"method": "stamp_trees", "sources": [], "detail": "crown"}, {"method": "stamp_trees", "sources": [], "detail": "crown"}, {"method": "stamp_trees", "sources": [], "detail": "crown"}, {"method": "stamp_trees", "sources": [], "detail": "crown"}, {"method": "stamp_trees", "sources": [], "detail": "crown"}, {"method": "stamp_trees", "sources": [], "detail": "crown"}, {"method": "stamp_trees", "sources": [], "detail": "crown"}, {"method": "stamp_trees", "sources": [], "detail": "crown"}, {"method": "stamp_trees", "sources": [], "detail": "crown"}, {"method": "stamp_trees", "sources": [], "detail": "crown"}, {"method": "stamp_trees", "sources": [], "detail": "trunk"}, {"method": "stamp_trees", "sources": [], "detail": "trunk"}, {"method": "stamp_trees", "sources": [], "detail": "trunk"}, {"method": "stamp_trees", "sources": [], "detail": "trunk"}, {"method": "seed_zone", "sources": [], "detail": "zone=grass"}, {"method": "seed_zone", "sources": [], "detail": "zone=grass"}, {"method": "seed_zone", "sources": [], "detail": "zone=grass"}, {"method": "seed_zone", "sources": [], "detail": "zone=path"}, {"method": "seed_zone", "sources": [], "detail": "zone=path"}, {"method": "seed_zone", "sources": [], "detail": "zone=path"}, {"method": "seed_zone", "sources": [], "detail": "zone=path"}, {"method": "seed_zone", "sources": [], "detail": "zone=grass"}, {"method": "seed_zone", "sources": [], "detail": "zone=grass"}, {"method": "seed_zone", "sources": [], "detail": "zone=grass"}, {"method": "stamp_trees", "sources": [], "detail": "crown_tip_grass"}, {"method": "stamp_trees", "sources": [], "detail": "crown_tip"}, {"method": "stamp_trees", "sources": [], "detail": "trunk"}, {"method": "stamp_trees", "sources": [], "detail": "trunk"}, {"method": "stamp_trees", "sources": [], "detail": "trunk"}, {"method": "stamp_trees", "sources": [], "detail": "trunk"}, {"method": "stamp_trees", "sources": [], "detail": "trunk"}, {"method": "stamp_trees", "sources": [], "detail": "trunk"}, {"method": "stamp_trees", "sources": [], "detail": "trunk"}, {"method": "stamp_trees", "sources": [], "detail": "trunk"}, {"method": "stamp_trees", "sources": [], "detail": "trunk"}, {"method": "stamp_trees", "sources": [], "detail": "trunk"}, {"method": "stamp_trees", "sources": [], "detail": "crown"}, {"method": "stamp_trees", "sources": [], "detail": "crown"}, {"method": "stamp_trees", "sources": [], "detail": "crown"}, {"method": "stamp_trees", "sources": [], "detail": "crown"}, {"method": "seed_zone", "sources": [], "detail": "zone=grass"}, {"method": "seed_zone", "sources": [], "detail": "zone=grass"}, {"method": "seed_zone", "sources": [], "detail": "zone=grass"}, {"method": "seed_zone", "sources": [], "detail": "zone=path"}, {"method": "seed_zone", "sources": [], "detail": "zone=path"}, {"method": "seed_zone", "sources": [], "detail": "zone=path"}, {"method": "seed_zone", "sources": [], "detail": "zone=grass"}, {"method": "seed_zone", "sources": [], "detail": "zone=grass"}, {"method": "seed_zone", "sources": [], "detail": "zone=grass"}, {"method": "seed_zone", "sources": [], "detail": "zone=grass"}, {"method": "stamp_trees", "sources": [], "detail": "crown"}, {"method": "stamp_trees", "sources": [], "detail": "crown"}, {"method": "stamp_trees", "sources": [], "detail": "crown"}, {"method": "stamp_trees", "sources": [], "detail": "crown"}, {"method": "stamp_trees", "sources": [], "detail": "crown"}, {"method": "stamp_trees", "sources": [], "detail": "crown"}, {"method": "stamp_trees", "sources": [], "detail": "crown"}, {"method": "stamp_trees", "sources": [], "detail": "crown"}, {"method": "stamp_trees", "sources": [], "detail": "crown"}, {"method": "stamp_trees", "sources": [], "detail": "crown"}, {"method": "stamp_trees", "sources": [], "detail": "crown"}, {"method": "stamp_trees", "sources": [], "detail": "crown"}, {"method": "stamp_trees", "sources": [], "detail": "trunk"}, {"method": "stamp_trees", "sources": [], "detail": "trunk"}, {"method": "stamp_trees", "sources": [], "detail": "trunk"}, {"method": "stamp_trees", "sources": [], "detail": "trunk"}, {"method": "seed_zone", "sources": [], "detail": "zone=grass"}, {"method": "seed_zone", "sources": [], "detail": "zone=grass"}, {"method": "seed_zone", "sources": [], "detail": "zone=grass"}, {"method": "seed_zone", "sources": [], "detail": "zone=path"}, {"method": "seed_zone", "sources": [], "detail": "zone=path"}, {"method": "seed_zone", "sources": [], "detail": "zone=path"}, {"method": "seed_zone", "sources": [], "detail": "zone=path"}, {"method": "seed_zone", "sources": [], "detail": "zone=grass"}, {"method": "seed_zone", "sources": [], "detail": "zone=grass"}, {"method": "seed_zone", "sources": [], "detail": "zone=grass"}, {"method": "stamp_trees", "sources": [], "detail": "bottom_trunk"}, {"method": "stamp_trees", "sources": [], "detail": "bottom_trunk"}, {"method": "stamp_trees", "sources": [], "detail": "trunk"}, {"method": "stamp_trees", "sources": [], "detail": "trunk"}, {"method": "stamp_trees", "sources": [], "detail": "bottom_trunk"}, {"method": "stamp_trees", "sources": [], "detail": "bottom_trunk"}, {"method": "stamp_trees", "sources": [], "detail": "bottom_trunk"}, {"method": "stamp_trees", "sources": [], "detail": "bottom_trunk"}, {"method": "stamp_trees", "sources": [], "detail": "bottom_trunk"}, {"method": "stamp_trees", "sources": [], "detail": "bottom_trunk"}, {"method": "stamp_trees", "sources": [], "detail": "trunk"}, {"method": "stamp_trees", "sources": [], "detail": "trunk"}, {"method": "stamp_trees", "sources": [], "detail": "crown"}, {"method": "stamp_trees", "sources": [], "detail": "crown"}, {"method": "stamp_trees", "sources": [], "detail": "crown"}, {"method": "stamp_trees", "sources": [], "detail": "crown"}, {"method": "seed_zone", "sources": [], "detail": "zone=grass"}, {"method": "seed_zone", "sources": [], "detail": "zone=grass"}, {"method": "seed_zone", "sources": [], "detail": "zone=grass"}, {"method": "seed_zone", "sources": [], "detail": "zone=path"}, {"method": "seed_zone", "sources": [], "detail": "zone=path"}, {"method": "seed_zone", "sources": [], "detail": "zone=path"}, {"method": "seed_zone", "sources": [], "detail": "zone=path"}, {"method": "seed_zone", "sources": [], "detail": "zone=grass"}, {"method": "seed_zone", "sources": [], "detail": "zone=grass"}, {"method": "seed_zone", "sources": [], "detail": "zone=grass"}, {"method": "seed_zone", "sources": [], "detail": "zone=grass"}, {"method": "stamp_trees", "sources": [], "detail": "unpaired_fallback_grass"}, {"method": "stamp_trees", "sources": [], "detail": "crown"}, {"method": "stamp_trees", "sources": [], "detail": "crown"}, {"method": "stamp_trees", "sources": [], "detail": "unpaired_fallback_grass"}, {"method": "seed_zone", "sources": [], "detail": "zone=water"}, {"method": "seed_zone", "sources": [], "detail": "zone=water"}, {"method": "seed_zone", "sources": [], "detail": "zone=water"}, {"method": "seed_zone", "sources": [], "detail": "zone=water"}, {"method": "seed_zone", "sources": [], "detail": "zone=water"}, {"method": "stamp_trees", "sources": [], "detail": "crown"}, {"method": "stamp_trees", "sources": [], "detail": "crown"}, {"method": "stamp_trees", "sources": [], "detail": "trunk"}, {"method": "stamp_trees", "sources": [], "detail": "trunk"}, {"method": "stamp_trees", "sources": [], "detail": "trunk"}, {"method": "stamp_trees", "sources": [], "detail": "trunk"}, {"method": "seed_zone", "sources": [], "detail": "zone=grass"}, {"method": "seed_zone", "sources": [], "detail": "zone=grass"}, {"method": "seed_zone", "sources": [], "detail": "zone=grass"}, {"method": "seed_zone", "sources": [], "detail": "zone=grass"}, {"method": "seed_zone", "sources": [], "detail": "zone=path"}, {"method": "seed_zone", "sources": [], "detail": "zone=path"}, {"method": "seed_zone", "sources": [], "detail": "zone=path"}, {"method": "seed_zone", "sources": [], "detail": "zone=path"}, {"method": "seed_zone", "sources": [], "detail": "zone=grass"}, {"method": "seed_zone", "sources": [], "detail": "zone=grass"}, {"method": "seed_zone", "sources": [], "detail": "zone=grass"}, {"method": "stamp_trees", "sources": [], "detail": "unpaired_fallback_grass"}, {"method": "stamp_trees", "sources": [], "detail": "bottom_trunk"}, {"method": "stamp_trees", "sources": [], "detail": "bottom_trunk"}, {"method": "stamp_trees", "sources": [], "detail": "unpaired_fallback_grass"}, {"method": "seed_zone", "sources": [], "detail": "zone=water"}, {"method": "seed_zone", "sources": [], "detail": "zone=water"}, {"method": "seed_zone", "sources": [], "detail": "zone=water"}, {"method": "seed_zone", "sources": [], "detail": "zone=water"}, {"method": "seed_zone", "sources": [], "detail": "zone=water"}, {"method": "stamp_trees", "sources": [], "detail": "trunk"}, {"method": "stamp_trees", "sources": [], "detail": "trunk"}, {"method": "stamp_trees", "sources": [], "detail": "crown"}, {"method": "stamp_trees", "sources": [], "detail": "crown"}, {"method": "stamp_trees", "sources": [], "detail": "crown"}, {"method": "stamp_trees", "sources": [], "detail": "crown"}, {"method": "stamp_trees", "sources": [], "detail": "unpaired_fallback_grass"}, {"method": "seed_zone", "sources": [], "detail": "zone=grass"}, {"method": "seed_zone", "sources": [], "detail": "zone=grass"}, {"method": "seed_zone", "sources": [], "detail": "zone=grass"}, {"method": "seed_zone", "sources": [], "detail": "zone=path"}, {"method": "seed_zone", "sources": [], "detail": "zone=path"}, {"method": "seed_zone", "sources": [], "detail": "zone=path"}, {"method": "seed_zone", "sources": [], "detail": "zone=path"}, {"method": "seed_zone", "sources": [], "detail": "zone=grass"}, {"method": "seed_zone", "sources": [], "detail": "zone=grass"}, {"method": "seed_zone", "sources": [], "detail": "zone=grass"}, {"method": "seed_zone", "sources": [], "detail": "zone=grass"}, {"method": "stamp_trees", "sources": [], "detail": "unpaired_fallback_grass"}, {"method": "stamp_trees", "sources": [], "detail": "unpaired_fallback_grass"}, {"method": "stamp_trees", "sources": [], "detail": "unpaired_fallback_grass"}, {"method": "seed_zone", "sources": [], "detail": "zone=water"}, {"method": "seed_zone", "sources": [], "detail": "zone=water"}, {"method": "seed_zone", "sources": [], "detail": "zone=water"}, {"method": "seed_zone", "sources": [], "detail": "zone=water"}, {"method": "seed_zone", "sources": [], "detail": "zone=water"}, {"method": "stamp_trees", "sources": [], "detail": "crown"}, {"method": "stamp_trees", "sources": [], "detail": "crown"}, {"method": "stamp_trees", "sources": [], "detail": "trunk"}, {"method": "stamp_trees", "sources": [], "detail": "trunk"}, {"method": "stamp_trees", "sources": [], "detail": "trunk"}, {"method": "stamp_trees", "sources": [], "detail": "trunk"}, {"method": "stamp_trees", "sources": [], "detail": "crown_tip"}, {"method": "stamp_trees", "sources": [], "detail": "crown_tip_grass"}, {"method": "seed_zone", "sources": [], "detail": "zone=grass"}, {"method": "seed_zone", "sources": [], "detail": "zone=grass"}, {"method": "seed_zone", "sources": [], "detail": "zone=grass"}, {"method": "seed_zone", "sources": [], "detail": "zone=path"}, {"method": "seed_zone", "sources": [], "detail": "zone=path"}, {"method": "seed_zone", "sources": [], "detail": "zone=path"}, {"method": "seed_zone", "sources": [], "detail": "zone=path"}, {"method": "seed_zone", "sources": [], "detail": "zone=grass"}, {"method": "seed_zone", "sources": [], "detail": "zone=grass"}, {"method": "seed_zone", "sources": [], "detail": "zone=grass"}, {"method": "seed_zone", "sources": [], "detail": "zone=grass"}, {"method": "stamp_trees", "sources": [], "detail": "unpaired_fallback_grass"}, {"method": "stamp_trees", "sources": [], "detail": "unpaired_fallback_grass"}, {"method": "seed_zone", "sources": [], "detail": "zone=water"}, {"method": "seed_zone", "sources": [], "detail": "zone=water"}, {"method": "seed_zone", "sources": [], "detail": "zone=water"}, {"method": "seed_zone", "sources": [], "detail": "zone=water"}, {"method": "seed_zone", "sources": [], "detail": "zone=water"}, {"method": "stamp_trees", "sources": [], "detail": "trunk"}, {"method": "stamp_trees", "sources": [], "detail": "trunk"}, {"method": "stamp_trees", "sources": [], "detail": "crown"}, {"method": "stamp_trees", "sources": [], "detail": "crown"}, {"method": "stamp_trees", "sources": [], "detail": "crown"}, {"method": "stamp_trees", "sources": [], "detail": "crown"}, {"method": "stamp_trees", "sources": [], "detail": "crown"}, {"method": "stamp_trees", "sources": [], "detail": "crown"}, {"method": "seed_zone", "sources": [], "detail": "zone=grass"}, {"method": "seed_zone", "sources": [], "detail": "zone=grass"}, {"method": "seed_zone", "sources": [], "detail": "zone=grass"}, {"method": "seed_zone", "sources": [], "detail": "zone=path"}, {"method": "seed_zone", "sources": [], "detail": "zone=path"}, {"method": "seed_zone", "sources": [], "detail": "zone=path"}, {"method": "seed_zone", "sources": [], "detail": "zone=path"}, {"method": "seed_zone", "sources": [], "detail": "zone=path"}, {"method": "seed_zone", "sources": [], "detail": "zone=grass"}, {"method": "seed_zone", "sources": [], "detail": "zone=grass"}, {"method": "seed_zone", "sources": [], "detail": "zone=grass"}, {"method": "seed_zone", "sources": [], "detail": "zone=grass"}, {"method": "stamp_trees", "sources": [], "detail": "unpaired_fallback_grass"}, {"method": "seed_zone", "sources": [], "detail": "zone=water"}, {"method": "seed_zone", "sources": [], "detail": "zone=water"}, {"method": "seed_zone", "sources": [], "detail": "zone=water"}, {"method": "seed_zone", "sources": [], "detail": "zone=water"}, {"method": "seed_zone", "sources": [], "detail": "zone=water"}, {"method": "stamp_trees", "sources": [], "detail": "crown"}, {"method": "stamp_trees", "sources": [], "detail": "crown"}, {"method": "stamp_trees", "sources": [], "detail": "trunk"}, {"method": "stamp_trees", "sources": [], "detail": "trunk"}, {"method": "stamp_trees", "sources": [], "detail": "trunk"}, {"method": "stamp_trees", "sources": [], "detail": "trunk"}, {"method": "stamp_trees", "sources": [], "detail": "trunk"}, {"method": "stamp_trees", "sources": [], "detail": "trunk"}, {"method": "stamp_trees", "sources": [], "detail": "crown_tip_grass"}, {"method": "stamp_trees", "sources": [], "detail": "crown_tip_grass"}, {"method": "stamp_trees", "sources": [], "detail": "crown_tip_grass"}, {"method": "stamp_trees", "sources": [], "detail": "crown_tip_grass"}, {"method": "stamp_trees", "sources": [], "detail": "crown_tip"}, {"method": "stamp_trees", "sources": [], "detail": "crown_tip"}, {"method": "stamp_trees", "sources": [], "detail": "crown_tip"}, {"method": "stamp_trees", "sources": [], "detail": "crown_tip"}, {"method": "seed_zone", "sources": [], "detail": "zone=path"}, {"method": "seed_zone", "sources": [], "detail": "zone=grass"}, {"method": "stamp_trees", "sources": [], "detail": "crown_tip_grass"}, {"method": "stamp_trees", "sources": [], "detail": "crown_tip_grass"}, {"method": "stamp_trees", "sources": [], "detail": "crown_tip_grass"}, {"method": "crown_tip_fixup", "sources": [{"x": 19, "y": 16, "reason": "crown_below"}], "detail": "added_tip_above_crown"}, {"method": "crown_tip_fixup", "sources": [{"x": 20, "y": 16, "reason": "crown_below"}], "detail": "added_tip_above_crown"}, {"method": "crown_tip_fixup", "sources": [{"x": 21, "y": 16, "reason": "crown_below"}], "detail": "added_tip_above_crown"}, {"method": "crown_tip_fixup", "sources": [{"x": 22, "y": 16, "reason": "crown_below"}], "detail": "added_tip_above_crown"}, {"method": "crown_tip_fixup", "sources": [{"x": 23, "y": 16, "reason": "crown_below"}], "detail": "added_tip_above_crown"}, {"method": "stamp_trees", "sources": [], "detail": "trunk"}, {"method": "stamp_trees", "sources": [], "detail": "trunk"}, {"method": "stamp_trees", "sources": [], "detail": "crown"}, {"method": "stamp_trees", "sources": [], "detail": "crown"}, {"method": "stamp_trees", "sources": [], "detail": "crown"}, {"method": "stamp_trees", "sources": [], "detail": "crown"}, {"method": "stamp_trees", "sources": [], "detail": "crown"}, {"method": "stamp_trees", "sources": [], "detail": "crown"}, {"method": "stamp_trees", "sources": [], "detail": "crown"}, {"method": "stamp_trees", "sources": [], "detail": "crown"}, {"method": "stamp_trees", "sources": [], "detail": "crown"}, {"method": "stamp_trees", "sources": [], "detail": "crown"}, {"method": "stamp_trees", "sources": [], "detail": "crown"}, {"method": "stamp_trees", "sources": [], "detail": "crown"}, {"method": "stamp_trees", "sources": [], "detail": "crown"}, {"method": "stamp_trees", "sources": [], "detail": "crown"}, {"method": "seed_zone", "sources": [], "detail": "zone=path"}, {"method": "seed_zone", "sources": [], "detail": "zone=path"}, {"method": "stamp_trees", "sources": [], "detail": "crown"}, {"method": "stamp_trees", "sources": [], "detail": "crown"}, {"method": "stamp_trees", "sources": [], "detail": "crown"}, {"method": "stamp_trees", "sources": [], "detail": "crown"}, {"method": "stamp_trees", "sources": [], "detail": "crown"}, {"method": "stamp_trees", "sources": [], "detail": "crown"}, {"method": "stamp_trees", "sources": [], "detail": "crown"}, {"method": "stamp_trees", "sources": [], "detail": "crown"}, {"method": "stamp_trees", "sources": [], "detail": "crown"}, {"method": "stamp_trees", "sources": [], "detail": "crown"}, {"method": "stamp_trees", "sources": [], "detail": "bottom_trunk"}, {"method": "stamp_trees", "sources": [], "detail": "bottom_trunk"}, {"method": "stamp_trees", "sources": [], "detail": "bottom_trunk"}, {"method": "stamp_trees", "sources": [], "detail": "bottom_trunk"}, {"method": "stamp_trees", "sources": [], "detail": "trunk"}, {"method": "stamp_trees", "sources": [], "detail": "trunk"}, {"method": "stamp_trees", "sources": [], "detail": "trunk"}, {"method": "stamp_trees", "sources": [], "detail": "trunk"}, {"method": "stamp_trees", "sources": [], "detail": "trunk"}, {"method": "stamp_trees", "sources": [], "detail": "trunk"}, {"method": "stamp_trees", "sources": [], "detail": "trunk"}, {"method": "stamp_trees", "sources": [], "detail": "trunk"}, {"method": "stamp_trees", "sources": [], "detail": "trunk"}, {"method": "stamp_trees", "sources": [], "detail": "trunk"}, {"method": "connection_seed", "sources": [], "detail": "from=Nulltown dir=down tree=False"}, {"method": "connection_seed", "sources": [], "detail": "from=Nulltown dir=down tree=False"}, {"method": "stamp_trees", "sources": [], "detail": "trunk"}, {"method": "stamp_trees", "sources": [], "detail": "trunk"}, {"method": "stamp_trees", "sources": [], "detail": "trunk"}, {"method": "stamp_trees", "sources": [], "detail": "trunk"}, {"method": "stamp_trees", "sources": [], "detail": "trunk"}, {"method": "stamp_trees", "sources": [], "detail": "trunk"}, {"method": "stamp_trees", "sources": [], "detail": "trunk"}, {"method": "stamp_trees", "sources": [], "detail": "trunk"}, {"method": "stamp_trees", "sources": [], "detail": "bottom_trunk"}, {"method": "stamp_trees", "sources": [], "detail": "bottom_trunk"}]